colort/__init__.py
colort/colort.py
colort/py.typed
colort/version.py
colort-1.0.1.dist-info/LICENSE
colort-1.0.1.dist-info/METADATA
colort-1.0.1.dist-info/WHEEL
colort-1.0.1.dist-info/top_level.txt
colort-1.0.1.dist-info/RECORD
