Metadata-Version: 2.1
Name: colort
Version: 1.0.1
Summary: Display colored text in the terminal.
Author-email: thep0y <thepoy@163.com>
License: MIT License
Project-URL: homepage, https://github.com/thep0y/colort
Project-URL: repository, https://github.com/thep0y/colort
Keywords: color,terminal
Classifier: Programming Language :: Python :: 3
Requires-Python: >=3
License-File: LICENSE
